pyresourcepool/__init__.py
pyresourcepool/pyresourcepool.py
PyResourcePool-0.1.12.dist-info/LICENSE
PyResourcePool-0.1.12.dist-info/METADATA
PyResourcePool-0.1.12.dist-info/WHEEL
PyResourcePool-0.1.12.dist-info/top_level.txt
PyResourcePool-0.1.12.dist-info/RECORD
