Metadata-Version: 2.1
Name: PyResourcePool
Version: 0.1.12
Summary: Provides a thread safe resource pool
Home-page: http://pypi.python.org/pypi/PyResourcePool/
Author: Jason Milen
Author-email: jpmilen@gmail.com
License: LICENSE.txt
Platform: UNKNOWN
Classifier: Programming Language :: Python :: 3
Classifier: License :: OSI Approved :: MIT License
Classifier: Operating System :: OS Independent
